pandas_x/__init__.py
pandas_x/_decorators.py
pandas_x/accessor.py
pandas_x/algorithms.py
pandas_x/scalar.py
pandas_x-0.0.4.dist-info/LICENSE
pandas_x-0.0.4.dist-info/METADATA
pandas_x-0.0.4.dist-info/WHEEL
pandas_x-0.0.4.dist-info/top_level.txt
pandas_x-0.0.4.dist-info/RECORD
