Metadata-Version: 2.1
Name: pandas-x
Version: 0.0.4
Summary: GPS/position calculation accessor for pandas DataFrames.
Home-page: https://github.com/aaron-schroeder/pandas-x
Author: Aaron Schroeder
Author-email: aaron@trailzealot.com
License: MIT
Project-URL: Documentation, https://pandas-x.readthedocs.io/en/v0.0.4/
Platform: UNKNOWN
Classifier: License :: OSI Approved :: MIT License
Classifier: Intended Audience :: Developers
Classifier: Programming Language :: Python :: 3
Classifier: Programming Language :: Python :: 3.7
Requires-Dist: numpy
Requires-Dist: pandas
